mongograph/__init__.py
mongograph/graph_easy.py
mongograph/mongo_wrapper/__init__.py
mongograph/mongo_wrapper/_mongo_wrapper.py
mongograph-0.0.4.dist-info/LICENSE
mongograph-0.0.4.dist-info/METADATA
mongograph-0.0.4.dist-info/WHEEL
mongograph-0.0.4.dist-info/top_level.txt
mongograph-0.0.4.dist-info/RECORD
