Metadata-Version: 2.1
Name: mongograph
Version: 0.0.4
Summary: Build Graphs On MongoDB Easily
Home-page: https://github.com/AbhishekPawaskar/MongoGraph.git
Author: Abhishek Pawaskar
Author-email: Abhishek99rp@gmail.com
Keywords: mongograph,grepheasy,graph_easy,GRAPH_EASY
Platform: Windows
Platform: Linux
Classifier: Development Status :: 4 - Beta
Classifier: License :: OSI Approved :: Apache Software License
Classifier: Programming Language :: Python :: 3.10
Classifier: Topic :: Database :: Database Engines/Servers
Requires-Python: >=3.10
License-File: LICENSE
Requires-Dist: pymongo (==4.3.3)
Requires-Dist: dnspython (==2.3.0)
